terraforminstaller/__init__.py
terraforminstaller/main.py
terraform_installer-1.0.1.dist-info/LICENSE
terraform_installer-1.0.1.dist-info/METADATA
terraform_installer-1.0.1.dist-info/WHEEL
terraform_installer-1.0.1.dist-info/entry_points.txt
terraform_installer-1.0.1.dist-info/top_level.txt
terraform_installer-1.0.1.dist-info/RECORD
