Metadata-Version: 2.1
Name: terraform-installer
Version: 1.0.1
Summary: install or upgrade the open source version of terraform.
Home-page: https://gitlab.com/shindagger/terraform-installer
Author: Andy Klier
Author-email: andyklier@gmail.com
License: UNKNOWN
Platform: UNKNOWN
Classifier: Programming Language :: Python :: 3
Classifier: License :: OSI Approved :: MIT License
Classifier: Operating System :: OS Independent
Requires-Python: >=3.6
Requires-Dist: setuptools
Requires-Dist: string-color
Requires-Dist: beautifulsoup4
Requires-Dist: requests
Requires-Dist: tqdm
Requires-Dist: pywin32 ; platform_system == "Windows"
